base/__init__.py
base/admin.py
base/apps.py
base/managers.py
base/models.py
base/tests.py
base/views.py
base/migrations/__init__.py
users/__init__.py
users/admin.py
users/apps.py
users/managers.py
users/models.py
users/permissions.py
users/serializers.py
users/settings.py
users/tests.py
users/urls.py
users/views.py
users/viewsets.py
users/migrations/0001_initial.py
users/migrations/0002_user_rol_usuario.py
users/migrations/__init__.py
users/migrations/__pycache__/0001_initial.cpython-311.pyc
users/migrations/__pycache__/__init__.cpython-311.pyc
django_users_auth-2.4.16.dist-info/LICENSE
django_users_auth-2.4.16.dist-info/METADATA
django_users_auth-2.4.16.dist-info/WHEEL
django_users_auth-2.4.16.dist-info/top_level.txt
django_users_auth-2.4.16.dist-info/RECORD
